oresat_star_tracker/__init__.py
oresat_star_tracker/__main__.py
oresat_star_tracker/_version.py
oresat_star_tracker/camera.py
oresat_star_tracker/star_tracker_service.py
oresat_star_tracker/templates/star_tracker.html
oresat_star_tracker-0.3.1.dist-info/LICENSE
oresat_star_tracker-0.3.1.dist-info/METADATA
oresat_star_tracker-0.3.1.dist-info/WHEEL
oresat_star_tracker-0.3.1.dist-info/entry_points.txt
oresat_star_tracker-0.3.1.dist-info/top_level.txt
oresat_star_tracker-0.3.1.dist-info/RECORD
